{
  "AE": [
    "AE/AE2007.pdf",
    "AE/AE2008.pdf",
    "AE/AE2009.pdf",
    "AE/AE2010.pdf",
    "AE/AE2011.pdf",
    "AE/AE2012.pdf",
    "AE/AE2013.pdf",
    "AE/AE2014.pdf",
    "AE/AE2015.pdf",
    "AE/AE2016.pdf",
    "AE/AE2017.pdf",
    "AE/AE2018.pdf",
    "AE/AE2019.pdf",
    "AE/AE2020.pdf",
    "AE/AE2021.pdf",
    "AE/AE2022.pdf",
    "AE/AE2023.pdf",
    "AE/AE2024.pdf",
    "AE/AE2025.pdf"
  ],
  "AG": [
    "AG/AG2007.pdf",
    "AG/AG2008.pdf",
    "AG/AG2009.pdf",
    "AG/AG2010.pdf",
    "AG/AG2011.pdf",
    "AG/AG2012.pdf",
    "AG/AG2013.pdf",
    "AG/AG2014.pdf",
    "AG/AG2015.pdf",
    "AG/AG2016.pdf",
    "AG/AG2017.pdf",
    "AG/AG2018.pdf",
    "AG/AG2019.pdf",
    "AG/AG2020.pdf",
    "AG/AG2021.pdf",
    "AG/AG2022.pdf",
    "AG/AG2023.pdf",
    "AG/AG2024.pdf",
    "AG/AG2025.pdf"
  ],
  "AR": [
    "AR/AR2007.pdf",
    "AR/AR2008.pdf",
    "AR/AR2009.pdf",
    "AR/AR2010.pdf",
    "AR/AR2011.pdf",
    "AR/AR2012.pdf",
    "AR/AR2013.pdf",
    "AR/AR2014.pdf",
    "AR/AR2015.pdf",
    "AR/AR2016.pdf",
    "AR/AR2017.pdf",
    "AR/AR2018.pdf",
    "AR/AR2019.pdf",
    "AR/AR2020.pdf",
    "AR/AR2021.pdf",
    "AR/AR2022.pdf",
    "AR/AR2023.pdf",
    "AR/AR2024.pdf"
  ],
  "BM": [
    "BM/BM2020.pdf",
    "BM/BM2021.pdf",
    "BM/BM2022.pdf",
    "BM/BM2023.pdf",
    "BM/BM2024.pdf"
  ],
  "BT": [
    "BT/BT2010.pdf",
    "BT/BT2011.pdf",
    "BT/BT2012.pdf",
    "BT/BT2013.pdf",
    "BT/BT2014.pdf",
    "BT/BT2015.pdf",
    "BT/BT2016.pdf",
    "BT/BT2017.pdf",
    "BT/BT2018.pdf",
    "BT/BT2019.pdf",
    "BT/BT2020.pdf",
    "BT/BT2021.pdf",
    "BT/BT2022.pdf",
    "BT/BT2023.pdf",
    "BT/BT2024.pdf",
    "BT/BT2025.pdf"
  ],
  "CE": [
    "CE/CE1-2017.pdf",
    "CE/CE1-2018.pdf",
    "CE/CE1-2019.pdf",
    "CE/CE1-2020.pdf",
    "CE/CE1-2021.pdf",
    "CE/CE1-2022.pdf",
    "CE/CE1-2023.pdf",
    "CE/CE12024.pdf",
    "CE/CE12025.pdf",
    "CE/CE2-2017.pdf",
    "CE/CE2-2018.pdf",
    "CE/CE2-2019.pdf",
    "CE/CE2-2020.pdf",
    "CE/CE2-2021.pdf",
    "CE/CE2-2022.pdf",
    "CE/CE2-2023.pdf",
    "CE/CE2007.pdf",
    "CE/CE2008.pdf",
    "CE/CE2009.pdf",
    "CE/CE2010.pdf",
    "CE/CE2011.pdf",
    "CE/CE2012.pdf",
    "CE/CE2013.pdf",
    "CE/CE2014.pdf",
    "CE/CE2015.pdf",
    "CE/CE2016.pdf",
    "CE/CE22024.pdf",
    "CE/CE22025.pdf"
  ],
  "CH": [
    "CH/CH2007.pdf",
    "CH/CH2008.pdf",
    "CH/CH2009.pdf",
    "CH/CH2010.pdf",
    "CH/CH2011.pdf",
    "CH/CH2012.pdf",
    "CH/CH2013.pdf",
    "CH/CH2014.pdf",
    "CH/CH2015.pdf",
    "CH/CH2016.pdf",
    "CH/CH2017.pdf",
    "CH/CH2018.pdf",
    "CH/CH2019.pdf",
    "CH/CH2020.pdf",
    "CH/CH2021.pdf",
    "CH/CH2022.pdf",
    "CH/CH2023.pdf",
    "CH/CH2024.pdf",
    "CH/CH2025.pdf"
  ],
  "CS": [
    "CS/CS1-2017.pdf",
    "CS/CS1-2021.pdf",
    "CS/CS12024.pdf",
    "CS/CS12025.pdf",
    "CS/CS2-2017.pdf",
    "CS/CS2-2021.pdf",
    "CS/CS2007.pdf",
    "CS/CS2008.pdf",
    "CS/CS2009.pdf",
    "CS/CS2010.pdf",
    "CS/CS2011.pdf",
    "CS/CS2012.pdf",
    "CS/CS2013.pdf",
    "CS/CS2014.pdf",
    "CS/CS2015.pdf",
    "CS/CS2016.pdf",
    "CS/CS2018.pdf",
    "CS/CS2019.pdf",
    "CS/CS2020.pdf",
    "CS/CS2022.pdf",
    "CS/CS2023.pdf",
    "CS/CS22024.pdf",
    "CS/CS22025.pdf"
  ],
  "CY": [
    "CY/CY2007.pdf",
    "CY/CY2008.pdf",
    "CY/CY2009.pdf",
    "CY/CY2010.pdf",
    "CY/CY2011.pdf",
    "CY/CY2012.pdf",
    "CY/CY2013.pdf",
    "CY/CY2014.pdf",
    "CY/CY2015.pdf",
    "CY/CY2016.pdf",
    "CY/CY2017.pdf",
    "CY/CY2018.pdf",
    "CY/CY2019.pdf",
    "CY/CY2020.pdf",
    "CY/CY2021.pdf",
    "CY/CY2022.pdf",
    "CY/CY2023.pdf",
    "CY/CY2024.pdf",
    "CY/CY2025.pdf"
  ],
  "DA": [
    "DA/DA2024.pdf",
    "DA/DA2025.pdf"
  ],
  "EC": [
    "EC/EC1-2017.pdf",
    "EC/EC2-2017.pdf",
    "EC/EC2007.pdf",
    "EC/EC2008.pdf",
    "EC/EC2009.pdf",
    "EC/EC2010.pdf",
    "EC/EC2011.pdf",
    "EC/EC2012.pdf",
    "EC/EC2013.pdf",
    "EC/EC2014.pdf",
    "EC/EC2015.pdf",
    "EC/EC2016.pdf",
    "EC/EC2018.pdf",
    "EC/EC2019.pdf",
    "EC/EC2020.pdf",
    "EC/EC2021.pdf",
    "EC/EC2022.pdf",
    "EC/EC2023.pdf",
    "EC/EC2024.pdf",
    "EC/EC2025.pdf"
  ],
  "EE": [
    "EE/EE1-2017.pdf",
    "EE/EE2-2017.pdf",
    "EE/EE2007.pdf",
    "EE/EE2008.pdf",
    "EE/EE2009.pdf",
    "EE/EE2010.pdf",
    "EE/EE2011.pdf",
    "EE/EE2012.pdf",
    "EE/EE2013.pdf",
    "EE/EE2014.pdf",
    "EE/EE2015.pdf",
    "EE/EE2016.pdf",
    "EE/EE2018.pdf",
    "EE/EE2019.pdf",
    "EE/EE2020.pdf",
    "EE/EE2021.pdf",
    "EE/EE2022.pdf",
    "EE/EE2023.pdf",
    "EE/EE2024.pdf",
    "EE/EE2025.pdf"
  ],
  "MA": [
    "MA/MA2007.pdf",
    "MA/MA2008.pdf",
    "MA/MA2009.pdf",
    "MA/MA2010.pdf",
    "MA/MA2011.pdf",
    "MA/MA2012.pdf",
    "MA/MA2013.pdf",
    "MA/MA2014.pdf",
    "MA/MA2015.pdf",
    "MA/MA2016.pdf",
    "MA/MA2017.pdf",
    "MA/MA2018.pdf",
    "MA/MA2019.pdf",
    "MA/MA2020.pdf",
    "MA/MA2021.pdf",
    "MA/MA2022.pdf",
    "MA/MA2023.pdf",
    "MA/MA2024.pdf",
    "MA/MA2025.pdf"
  ],
  "ME": [
    "ME/ME1-2017.pdf",
    "ME/ME1-2018.pdf",
    "ME/ME1-2019.pdf",
    "ME/ME1-2020.pdf",
    "ME/ME1-2021.pdf",
    "ME/ME1-2022.pdf",
    "ME/ME2-2017.pdf",
    "ME/ME2-2018.pdf",
    "ME/ME2-2019.pdf",
    "ME/ME2-2020.pdf",
    "ME/ME2-2021.pdf",
    "ME/ME2-2022.pdf",
    "ME/ME2007.pdf",
    "ME/ME2008.pdf",
    "ME/ME2009.pdf",
    "ME/ME2010.pdf",
    "ME/ME2011.pdf",
    "ME/ME2012.pdf",
    "ME/ME2013.pdf",
    "ME/ME2014.pdf",
    "ME/ME2015.pdf",
    "ME/ME2016.pdf",
    "ME/ME2023.pdf",
    "ME/ME2024.pdf",
    "ME/ME2025.pdf"
  ],
  "MN": [
    "MN/MN2007.pdf",
    "MN/MN2008.pdf",
    "MN/MN2009.pdf",
    "MN/MN2010.pdf",
    "MN/MN2011.pdf",
    "MN/MN2012.pdf",
    "MN/MN2013.pdf",
    "MN/MN2014.pdf",
    "MN/MN2015.pdf",
    "MN/MN2016.pdf",
    "MN/MN2017.pdf",
    "MN/MN2018.pdf",
    "MN/MN2019.pdf",
    "MN/MN2020.pdf",
    "MN/MN2021.pdf",
    "MN/MN2022.pdf",
    "MN/MN2023.pdf",
    "MN/MN2024.pdf",
    "MN/MN2025.pdf"
  ],
  "MT": [
    "MT/MT2007.pdf",
    "MT/MT2008.pdf",
    "MT/MT2009.pdf",
    "MT/MT2010.pdf",
    "MT/MT2011.pdf",
    "MT/MT2012.pdf",
    "MT/MT2013.pdf",
    "MT/MT2014.pdf",
    "MT/MT2015.pdf",
    "MT/MT2016.pdf",
    "MT/MT2017.pdf",
    "MT/MT2018.pdf",
    "MT/MT2019.pdf",
    "MT/MT2020.pdf",
    "MT/MT2021.pdf",
    "MT/MT2022.pdf",
    "MT/MT2023.pdf",
    "MT/MT2024.pdf",
    "MT/MT2025.pdf"
  ],
  "PE": [
    "PE/PE2016.pdf",
    "PE/PE2017.pdf",
    "PE/PE2018.pdf",
    "PE/PE2019.pdf",
    "PE/PE2020.pdf",
    "PE/PE2021.pdf",
    "PE/PE2022.pdf",
    "PE/PE2023.pdf",
    "PE/PE2024.pdf",
    "PE/PE2025.pdf"
  ],
  "PH": [
    "PH/PH2007.pdf",
    "PH/PH2008.pdf",
    "PH/PH2009.pdf",
    "PH/PH2010.pdf",
    "PH/PH2011.pdf",
    "PH/PH2012.pdf",
    "PH/PH2013.pdf",
    "PH/PH2014.pdf",
    "PH/PH2015.pdf",
    "PH/PH2016.pdf",
    "PH/PH2017.pdf",
    "PH/PH2018.pdf",
    "PH/PH2019.pdf",
    "PH/PH2020.pdf",
    "PH/PH2021.pdf",
    "PH/PH2022.pdf",
    "PH/PH2023.pdf",
    "PH/PH2024.pdf",
    "PH/PH2025.pdf"
  ],
  "PI": [
    "PI/PI2007.pdf",
    "PI/PI2008.pdf",
    "PI/PI2009.pdf",
    "PI/PI2010.pdf",
    "PI/PI2011.pdf",
    "PI/PI2012.pdf",
    "PI/PI2013.pdf",
    "PI/PI2014.pdf",
    "PI/PI2015.pdf",
    "PI/PI2016.pdf",
    "PI/PI2017.pdf",
    "PI/PI2018.pdf",
    "PI/PI2019.pdf",
    "PI/PI2020.pdf",
    "PI/PI2021.pdf",
    "PI/PI2022.pdf",
    "PI/PI2023.pdf",
    "PI/PI2024.pdf",
    "PI/PI2025.pdf"
  ],
  "ST": [
    "ST/ST2019.pdf",
    "ST/ST2020.pdf",
    "ST/ST2021.pdf",
    "ST/ST2022.pdf",
    "ST/ST2023.pdf",
    "ST/ST2024.pdf",
    "ST/ST2025.pdf"
  ]
}
